<?xml version="1.0" ?>
<SmellBaseline>
  <ManuallySuppressedIssues></ManuallySuppressedIssues>
  <CurrentIssues>
    <ID>ClassOrdering:OverlayService.kt$OverlayService$init { if (BuildConfig.DEBUG &amp;&amp; Timber.treeCount == 0) { Timber.plant(MethodLineLoggingTree()) } }</ID>
    <ID>ClassOrdering:OverlayService.kt$OverlayService$lateinit var overlayWindow: OverlayWindow</ID>
    <ID>ClassOrdering:OverlayService.kt$OverlayService$override fun onBind(intent: Intent): IBinder?</ID>
    <ID>ClassOrdering:OverlayService.kt$OverlayService$override fun onConfigurationChanged(newConfig: Configuration)</ID>
    <ID>ClassOrdering:OverlayService.kt$OverlayService$override fun onDestroy()</ID>
    <ID>ClassOrdering:OverlayService.kt$OverlayService$override fun onStartCommand(intent: Intent, flags: Int, startId: Int): Int</ID>
    <ID>ClassOrdering:OverlayService.kt$OverlayService$private fun getOverlayWindowHeight(): Int</ID>
    <ID>ClassOrdering:OverlayService.kt$OverlayService$private fun getOverlayWindowWidth(): Int</ID>
    <ID>EmptyClassBlock:ViewModelOverlayConfigureScreen.kt$ViewModelOverlayConfigureScreen${ }</ID>
    <ID>FunctionNaming:AboutDialog.kt$@Composable fun AboutDialog(openDialog: MutableState&lt;Boolean&gt;)</ID>
    <ID>FunctionNaming:AboutDialog.kt$@Composable fun AboutDialogRow(context: Context)</ID>
    <ID>FunctionNaming:AboutDialog.kt$@Preview @Composable fun PreviewAboutDialog()</ID>
    <ID>FunctionNaming:Greeting.kt$@Composable fun Greeting()</ID>
    <ID>FunctionNaming:MainScreen.kt$@Composable fun AppBar()</ID>
    <ID>FunctionNaming:MainScreen.kt$@Composable fun MainScreen( navController: NavController, viewModelPermission: ViewModelPermission )</ID>
    <ID>FunctionNaming:MainScreen.kt$@Composable fun PermissionButtons( viewModelPermission: ViewModelPermission )</ID>
    <ID>FunctionNaming:MainScreen.kt$@Composable fun Permissions( navController: NavController, viewModelPermission: ViewModelPermission )</ID>
    <ID>FunctionNaming:MainScreen.kt$@Composable fun SelectPhoto( navController: NavController, viewModelPermission: ViewModelPermission )</ID>
    <ID>FunctionNaming:MainScreen.kt$@Composable fun Usage()</ID>
    <ID>FunctionNaming:MainScreen.kt$@Preview( name = "Dark Theme, Landscape", widthDp = 720, heightDp = 720, uiMode = Configuration.UI_MODE_NIGHT_YES ) @Composable fun PreviewMainScreenLandscape()</ID>
    <ID>FunctionNaming:MainScreen.kt$@Preview(name = "Light Theme") @Composable fun PreviewMainScreenPortrait()</ID>
    <ID>FunctionNaming:PermissionScreen.kt$@Composable @Preview fun PreviewPermissionScreen()</ID>
    <ID>FunctionNaming:PermissionScreen.kt$@Composable fun DisplayOverOtherApps()</ID>
    <ID>FunctionNaming:PermissionScreen.kt$@Composable fun FilesAndMedia()</ID>
    <ID>FunctionNaming:PermissionScreen.kt$@Composable fun Location()</ID>
    <ID>FunctionNaming:PermissionScreen.kt$@Composable fun PermissionScreen(navController: NavController)</ID>
    <ID>FunctionNaming:PhotoCard.kt$@Composable fun PhotoCard(navController: NavController, photoCardData: PhotoCardData)</ID>
    <ID>FunctionNaming:PhotoCard.kt$@Preview @Composable fun CardPhotoPreview()</ID>
    <ID>FunctionNaming:PhotoDialogCollection.kt$@Composable fun ButtonStorageAccessFrameworkFile( radioStorageAccessFramework: String, selected: String )</ID>
    <ID>FunctionNaming:PhotoDialogCollection.kt$@Composable fun ButtonStorageAccessFrameworkFolder( radioStorageAccessFramework: String, selected: String )</ID>
    <ID>FunctionNaming:PhotoDialogCollection.kt$@Composable fun PhotoDialogCollection()</ID>
    <ID>FunctionNaming:PhotoDialogCollection.kt$@Composable fun PhotoDialogCollection(openDialog: MutableState&lt;Boolean&gt;)</ID>
    <ID>FunctionNaming:PhotoDialogCollection.kt$@Composable private fun RowMediaStore( radioMediaStore: String, selected: String, onSelectedChange: (String) -&gt; Unit )</ID>
    <ID>FunctionNaming:PhotoDialogCollection.kt$@Composable private fun RowStorageAccessFramework( radioStorageAccessFramework: String, selected: String, onSelectedChange: (String) -&gt; Unit )</ID>
    <ID>FunctionNaming:PhotoDialogCollection.kt$@Preview @Composable fun PreviewPhotoDialogCollection()</ID>
    <ID>FunctionNaming:PhotoDialogFilter.kt$@Composable fun FilterDialogRow()</ID>
    <ID>FunctionNaming:PhotoDialogFilter.kt$@Composable fun PhotoDialogFilter(openDialog: MutableState&lt;Boolean&gt;)</ID>
    <ID>FunctionNaming:PhotoDialogFilter.kt$@Preview @Composable fun PreviewPhotoDialogFilter()</ID>
    <ID>FunctionNaming:PhotoDialogSort.kt$@Composable fun PhotoDialogSort(openDialog: MutableState&lt;Boolean&gt;)</ID>
    <ID>FunctionNaming:PhotoDialogSort.kt$@Composable fun PhotoDialogSortRow()</ID>
    <ID>FunctionNaming:PhotoDialogSort.kt$@Composable private fun DistanceRow()</ID>
    <ID>FunctionNaming:PhotoDialogSort.kt$@Composable private fun WhenTakenRow()</ID>
    <ID>FunctionNaming:PhotoDialogSort.kt$@Preview @Composable fun PreviewPhotoDialogSort()</ID>
    <ID>FunctionNaming:PhotoSelectScreen.kt$@Composable fun PhotoSelectScreen(navController: NavController)</ID>
    <ID>FunctionNaming:PhotoSelectScreen.kt$@Composable fun TopBarActions( filterDialogState: MutableState&lt;Boolean&gt;, collectionDialogState: MutableState&lt;Boolean&gt;, sortDialogState: MutableState&lt;Boolean&gt; )</ID>
    <ID>FunctionNaming:PhotoSelectScreen.kt$@Preview(name = "Light Theme") @Composable fun PreviewPhotoSelectScreen()</ID>
    <ID>FunctionNaming:common.kt$@Composable fun ButtonOk(onClick: () -&gt; Unit)</ID>
    <ID>LongMethod:PhotoCard.kt$@Composable fun PhotoCard(navController: NavController, photoCardData: PhotoCardData)</ID>
    <ID>MagicNumber:Canny.kt$Canny$4</ID>
    <ID>MagicNumber:Canny.kt$Canny$80.0</ID>
    <ID>MagicNumber:EdgeDetectionUtils.kt$EdgeDetectionUtils$3.0</ID>
    <ID>MagicNumber:PhotoSelectScreen.kt$20</ID>
    <ID>MayBeConst:OverlayService.kt$OverlayService.Companion$val OVERLAY_WINDOW_HEIGHT_ADJUSTMENT = .80</ID>
    <ID>MayBeConst:OverlayService.kt$OverlayService.Companion$val OVERLAY_WINDOW_WIDTH_ADJUSTMENT = .75</ID>
    <ID>NewLineAtEndOfFile:PhotoCollection.kt$com.github.jameshnsears.cameraoverlay.model.photo.PhotoCollection.kt</ID>
    <ID>SpacingBetweenPackageAndImports:ViewModelOverlayConfigureScreen.kt$ </ID>
    <ID>UnusedImports:PhotoSelectScreen.kt$import androidx.compose.material.icons.outlined.Window</ID>
    <ID>UnusedPrivateMember:PhotoCard.kt$navController: NavController</ID>
  </CurrentIssues>
</SmellBaseline>
